Workbook

Sheet Guide
A1: ЛЗ8 SaparTravel | B1: Как использовать модель
A2: Версия / дата | B2: 1.1 KZT / 23.10.2026
A3: Единицы | B3: Тенге (KZT). Курс и дата — FX; опубликованные валютные тарифы переведены формулами. Налоги и инфляция не включены
A4: Статус | B4: Смета и гипотезы; фактические расходы и коммерческие договоры не подтверждены
A5: Горизонт бюджета | B5: 09.2026–08.2027; M1–M3 разработка, запуск до 20.12.2026; первые 4 месяца также план, не факт
A6: Редактирование | B6: Синие значения Inputs, исходные тарифы Tariffs B, FX B4:B6 и MAU Budget12 — входы; остальные суммы рассчитываются формулами
A7: Безубыточность | B7: Операционная отдельно от распределения разовых затрат на 36 месяцев; рост MAU не равен прибыли первого года
A8: Пересчет | B8: Открыть в Excel/LibreOffice с автоматическим пересчетом. Checks: все разности = 0, дефицит часов = 46,2
A9: Оплата | B9: Учетная запись и платные ресурсы облака не создавались; только публичный калькулятор и тарифы
A10: Резервы | B10: EMV 63,2 ч и управление 16 ч умножаются на ставку часа в тенге из Inputs; резервы — лимиты, не фактические расходы
A11: Поддержка | B11: Поддержка приложения и пользователей — ставка Inputs в тенге; 4/12/8 ч администрирования размещения учитываются отдельно
A12: Ограничение мощности | B12: Прогноз до 2000 MAU, 500 туров, БД до 10 GiB, 20 RPS суммарно; подтвердить нагрузочным тестом
A13: TCO | B13: Hosting: 36 полных месяцев одинакового спроса. Budget12: проект с разработкой и постепенным ростом; горизонты различаются

Sheet FX
A1: Валютный параметр | B1: Значение | C1: Правило использования
A2: Валюта бюджета | B2: KZT / казахстанский тенге | C2: Все итоговые затраты, выручка и стоимость на MAU — в тенге
A3: Валюта опубликованных тарифов | B3: USD | C3: Исходные тарифы провайдеров сохранены на Tariffs, колонка B
A4: Курс: тенге за 1 USD | B4: 447.94 | C4: Редактируемый курс; пересчитывает опубликованные валютные тарифы, колонка E Tariffs
A5: Дата курса | B5: 2026-10-23 | C5: Дата котировки/применения, зафиксированная при подготовке расчета
A6: Источник курса | B6: https://nationalbank.kz/rss/get_rates.cfm?fdate=23.10.2026 | C6: Проверяемый источник; ставка курса передана в конвертер явно
A7: Местные сметные допущения | B7: Фиксированы в тенге после перевода | C7: Inputs и ранний baseline переведены однократно по курсу на дату подготовки; менять в тенге по фактическим предложениям
A8: Что означает валютный стресс | B8: Меняются только опубликованные валютные тарифы | C8: Курс не индексирует местный чек, зарплаты, CAPEX и прочие фиксированные тенговые допущения
A9: Точность | B9: Формулы сохраняют полную точность; вывод денег — 2 знака | C9: Малые удельные ставки показаны с 4 знаками; остаток резерва переносится на M3
A10: Налоги, инфляция и банковская конвертация | B10: Не включены | C10: Перевод валюты сохраняет исходную методику, не является налоговым или банковским расчетом

Sheet Inputs
A1: Параметр | B1: Значение | C1: Единица | D1: Основание
A2: Стоимость разработки и настройки приложения | B2: 8062920 | C2: тг, разово | D2: Бизнес-кейс ЛЗ3; top-down оценка. Трудоемкость WBS оценивается отдельно, ставки указаны в тенге
A3: Миграция/сверка данных | B3: 671910 | C3: тг, разово | D3: Бизнес-кейс ЛЗ3
A4: Обучение пользователей | B4: 358352 | C4: тг, разово | D4: Бизнес-кейс ЛЗ3
A5: Вывод старого ручного процесса | B5: 223970 | C5: тг, разово | D5: Бизнес-кейс ЛЗ3; перенос в месяц запуска
A6: Поддержка приложения и пользователей | B6: 223970 | C6: тг/мес. после запуска | D6: 6000/12 из ЛЗ3; без администрирования хостинга
A7: Продвижение | B7: 44794 | C7: тг/мес. после запуска | D7: Учебное допущение ЛЗ8, не оферта
A8: Переменные расходы на активного туриста | B8: 89.588 | C8: тг/MAU/мес. | D8: Допущение: обработка и сверка операций; инфраструктура отдельно
A9: Средняя стоимость реализованного заказа | B9: 223970 | C9: тг/заказ | D9: Допущение, не цена демонстрационного каталога
A10: Доля MAU с одним реализованным заказом/мес. | B10: 0.03 | C10: доля | D10: Допущение; уже после отмен и неявок
A11: Комиссия поставщика | B11: 0.08 | C11: доля GMV | D11: Гипотеза договора: ручное выставление счета, без онлайн-оплаты
A12: Ставка дополнительного администрирования | B12: 4479.4 | C12: тг/ч | D12: Допущение ЛЗ3; полная стоимость часа с начислениями
A13: Часы администрирования cloud | B13: 4 | C13: ч/мес. | D13: Допущение, не круглосуточное дежурство
... A32: Ранний baseline ЛЗ3 для сравнения | B32: 20605240 | C32: тг, справочно | D32: Архивная смета ЛЗ3, приведенная к тенге по начальному курсу FX; не новая оценка затрат

Sheet Tariffs
A1: Тариф | B1: Исходный тариф USD / доля | C1: Источник | D1: Конфигурация / примечание | E1: Тариф в тенге / доля
A2: Cloud application VM | B2: 24 | C2: S02 | D2: Basic Regular 2 vCPU, 4 GiB, 80 GiB SSD | E2: =B2*FX!$B$4 -> 10750.56
A3: Managed PostgreSQL | B3: 30.45 | C3: S03 | D3: Standard Basic Regular 1 vCPU, 2 GiB, 30 GiB, 0 standby | E3: =B3*FX!$B$4 -> 13639.773
A4: Daily backup fraction | B4: 0.3 | C4: S04 | D4: Безразмерная доля от application VM; не денежная сумма | E4: =B4 -> 0.3
A5: Offsite object storage | B5: 5 | C5: S05 | D5: Spaces 250 GiB / 1 TiB; для own/rent вне основного сервера | E5: =B5*FX!$B$4 -> 2239.7
A6: External monitoring VM | B6: 6 | C6: S02 | D6: Basic 1 vCPU, 1 GiB; мониторинг, пробы и логи | E6: =B6*FX!$B$4 -> 2687.64
A7: Rent AX42-1 | B7: 117.1 | C7: S06/S08 | D7: Обычный dedicated FSN1/HEL1; 64 GB ECC, 2×512 GB | E7: =B7*FX!$B$4 -> 52453.774
A8: Rent primary IPv4 | B8: 1.9 | C8: S07 | D8: Ежемесячная цена; разовая настройка IPv4 — 0 тг | E8: =B8*FX!$B$4 -> 851.086
A9: Rent provider setup | B9: 59 | C9: S06 | D9: Разовый setup провайдера; исходный USD переведен в колонке E, не ежемесячный платеж | E9: =B9*FX!$B$4 -> 26428.46

Sheet Hosting
A1: Статья, тенге | B1: Cloud managed | C1: Собственное | D1: Open stack dedicated | E1: Правило
A2: Приложение / сервер | B2: =Tariffs!E2 -> 10750.56 | C2: 0 | D2: =Tariffs!E7 -> 52453.774 | E2: Доступен весь месяц; demand одинаковый, железо может быть избыточно
A3: Managed DB | B3: =Tariffs!E3 -> 13639.773 | C3: 0 | D3: 0 | E3: Для own/rent PostgreSQL на своем узле; лицензия — 0 тг
A4: Backup VM | B4: =Tariffs!E2*Tariffs!B4 -> 3225.168 | C4: 0 | D4: 0 | E4: Cloud daily image; отдельные логические копии БД — в Spaces
A5: Внешние копии / артефакты | B5: =Tariffs!E5 -> 2239.7 | C5: =Tariffs!E5 -> 2239.7 | D5: =Tariffs!E5 -> 2239.7 | E5: Один лимит на вариант; 7 daily + 4 weekly + 3 monthly при dump ≤ 5 GiB
A6: Мониторинг | B6: =Tariffs!E6 -> 2687.64 | C6: =Tariffs!E6 -> 2687.64 | D6: =Tariffs!E6 -> 2687.64 | E6: Отдельный узел; для cloud другой регион, для остальных другой провайдер
A7: Домен/DNS | B7: =Inputs!$B$16 -> 447.94 | C7: =Inputs!$B$16 -> 447.94 | D7: =Inputs!$B$16 -> 447.94 | E7: Годовой домен распределен на 12 месяцев; ставка Inputs указана в тенге
A8: Администрирование | B8: =Inputs!$B$12*Inputs!$B$13 -> 17917.6 | C8: =Inputs!$B$12*Inputs!$B$14 -> 53752.8 | D8: =Inputs!$B$12*Inputs!$B$15 -> 35835.2 | E8: Дополнительные часы администрирования; поддержка приложения учитывается отдельно
A9: Электроэнергия | B9: 0 | C9: =Inputs!$B$24*24*365/12*Inputs!$B$25 -> 3923.9544 | D9: 0 | E9: 80 W, 365 дней/год; для rent/cloud в цене
A10: Интернет / публичный IP | B10: 0 | C10: =Inputs!$B$26 -> 13438.2 | D10: =Tariffs!E8 -> 851.086 | E10: Cloud IPv4 и исходящий трафик в лимите плана
A11: Запчасти / обслуживание | B11: 0 | C11: =Inputs!$B$27 -> 4479.4 | D11: 0 | E11: У owned отдельная сметная статья
A12: Ежемесячно | B12: =SUM(B2:B11) -> 50908.381 | C12: =SUM(C2:C11) -> 80969.634 | D12: =SUM(D2:D11) -> 94515.34 | E12: OPEX размещения
A13: CAPEX | B13: 0 | C13: =Inputs!$B$22+Inputs!$B$23 -> 1119850 | D13: 0 | E13: Сервер + UPS/сеть; сметные CAPEX в тенге из Inputs
A14: Разовая настройка + setup | B14: =Inputs!$B$28*Inputs!$B$12 -> 17917.6 | C14: =Inputs!$B$29*Inputs!$B$12 -> 53752.8 | D14: =Inputs!$B$30*Inputs!$B$12+Tariffs!E9 -> 62263.66 | E14: Разовые работы инфраструктуры сверх разработки приложения; все суммы в тенге
A15: TCO размещения, 36 мес. | B15: =B12*36+B13+B14 -> 1850619.3 | C15: =C12*36+C13+C14 -> 4088509.6 | D15: =D12*36+D13+D14 -> 3464815.9 | E15: Без дисконтирования, инфляции и остаточной стоимости; CAPEX не амортизируется повторно
A16: Общие затраты продукта | B16: =Inputs!$B$2+Inputs!$B$3+Inputs!$B$4+Inputs!$B$5+Inputs!$B$6*36 -> 17380072 | C16: =B16 -> 17380072 | D16: =B16 -> 17380072 | E16: Разработка, миграция, обучение, переход и поддержка за 36 месяцев; без маркетинга и переменных расходов
A17: Сопоставимый TCO проекта | B17: =B15+B16 -> 19230691 | C17: =C15+C16 -> 21468582 | D17: =D15+D16 -> 20844888 | E17: Сопоставление с архивным baseline ЛЗ3, приведенным к тенге в Inputs
A18: Разница с ЛЗ3 | B18: =B17-Inputs!$B$32 -> -1374548.7 | C18: =C17-Inputs!$B$32 -> 863341.64 | D18: =D17-Inputs!$B$32 -> 239647.9 | E18: Уточнены статьи инфраструктуры; не новый замер ROI
A19: Тарифы +30%: TCO размещения | B19: =(B2+B3+B4+B5+B6)*0.3*36+B15 -> 2202082 | C19: =(C5+C6)*0.3*36+C15 -> 4141724.9 | D19: =(D2+D5+D6+D10)*0.3*36+D15 -> 4093723.7 | E19: Стресс только опубликованных ежемесячных тарифов; труд и CAPEX без роста

Sheet Budget12
A1: Статья / суммы в тенге | B1: M1 09.2026 | C1: M2 10.2026 | D1: M3 11.2026 | E1: M4 12.2026 | F1: M5 01.2027 | G1: M6 02.2027 | H1: M7 03.2027 | I1: M8 04.2027 | J1: M9 05.2027 | K1: M10 06.2027 | L1: M11 07.2027 | M1: M12 08.2027 | N1: 12 месяцев
A2: MAU туристов | B2: 0 | C2: 0 | D2: 0 | E2: 100 | F2: 200 | G2: 400 | H2: 600 | I2: 800 | J2: 1000 | K2: 1300 | L2: 1600 | M2: 2000 | N2: =SUM(B2:M2) -> 8000
A3: Разработка | B3: =Inputs!$B$2/3 -> 2687640 | C3: =Inputs!$B$2/3 -> 2687640 | D3: =Inputs!$B$2/3 -> 2687640 | E3: 0 | F3: 0 | G3: 0 | H3: 0 | I3: 0 | J3: 0 | K3: 0 | L3: 0 | M3: 0 | N3: =SUM(B3:M3) -> 8062920
A4: Миграция данных | B4: 0 | C4: 0 | D4: =Inputs!$B$3 -> 671910 | E4: 0 | F4: 0 | G4: 0 | H4: 0 | I4: 0 | J4: 0 | K4: 0 | L4: 0 | M4: 0 | N4: =SUM(B4:M4) -> 671910
A5: Обучение | B5: 0 | C5: 0 | D5: =Inputs!$B$4 -> 358352 | E5: 0 | F5: 0 | G5: 0 | H5: 0 | I5: 0 | J5: 0 | K5: 0 | L5: 0 | M5: 0 | N5: =SUM(B5:M5) -> 358352
A6: Вывод старого процесса | B6: 0 | C6: 0 | D6: 0 | E6: =Inputs!$B$5 -> 223970 | F6: 0 | G6: 0 | H6: 0 | I6: 0 | J6: 0 | K6: 0 | L6: 0 | M6: 0 | N6: =SUM(B6:M6) -> 223970
A7: Разовая настройка hosting | B7: =Hosting!$B$14 -> 17917.6 | C7: 0 | D7: 0 | E7: 0 | F7: 0 | G7: 0 | H7: 0 | I7: 0 | J7: 0 | K7: 0 | L7: 0 | M7: 0 | N7: =SUM(B7:M7) -> 17917.6
A8: Размещение и его администрирование | B8: =Hosting!$B$12 -> 50908.381 | C8: =Hosting!$B$12 -> 50908.381 | D8: =Hosting!$B$12 -> 50908.381 | E8: =Hosting!$B$12 -> 50908.381 | F8: =Hosting!$B$12 -> 50908.381 | G8: =Hosting!$B$12 -> 50908.381 | H8: =Hosting!$B$12 -> 50908.381 | I8: =Hosting!$B$12 -> 50908.381 | ... M8: =Hosting!$B$12 -> 50908.381 | N8: =SUM(B8:M8) -> 610900.57
A9: Поддержка приложения | B9: 0 | C9: 0 | D9: 0 | E9: =Inputs!$B$6 -> 223970 | F9: =Inputs!$B$6 -> 223970 | G9: =Inputs!$B$6 -> 223970 | H9: =Inputs!$B$6 -> 223970 | I9: =Inputs!$B$6 -> 223970 | J9: =Inputs!$B$6 -> 223970 | K9: =Inputs!$B$6 -> 223970 | L9: =Inputs!$B$6 -> 223970 | M9: =Inputs!$B$6 -> 223970 | N9: =SUM(B9:M9) -> 2015730
A10: Продвижение | B10: 0 | C10: 0 | D10: 0 | E10: =Inputs!$B$7 -> 44794 | F10: =Inputs!$B$7 -> 44794 | G10: =Inputs!$B$7 -> 44794 | H10: =Inputs!$B$7 -> 44794 | I10: =Inputs!$B$7 -> 44794 | J10: =Inputs!$B$7 -> 44794 | K10: =Inputs!$B$7 -> 44794 | L10: =Inputs!$B$7 -> 44794 | M10: =Inputs!$B$7 -> 44794 | N10: =SUM(B10:M10) -> 403146
A11: Переменные расходы | B11: =B2*Inputs!$B$8 -> 0 | C11: =C2*Inputs!$B$8 -> 0 | D11: =D2*Inputs!$B$8 -> 0 | E11: =E2*Inputs!$B$8 -> 8958.8 | F11: =F2*Inputs!$B$8 -> 17917.6 | G11: =G2*Inputs!$B$8 -> 35835.2 | H11: =H2*Inputs!$B$8 -> 53752.8 | I11: =I2*Inputs!$B$8 -> 71670.4 | ... M11: =M2*Inputs!$B$8 -> 179176 | N11: =SUM(B11:M11) -> 716704
A12: Плановые затраты без резервов | B12: =SUM(B3:B11) -> 2756466 | C12: =SUM(C3:C11) -> 2738548.4 | D12: =SUM(D3:D11) -> 3768810.4 | E12: =SUM(E3:E11) -> 552601.18 | F12: =SUM(F3:F11) -> 337589.98 | G12: =SUM(G3:G11) -> 355507.58 | H12: =SUM(H3:H11) -> 373425.18 | I12: =SUM(I3:I11) -> 391342.78 | ... M12: =SUM(M3:M11) -> 498848.38 | N12: =SUM(B12:M12) -> 13081550
A13: Выручка: комиссия | B13: =B2*Inputs!$B$9*Inputs!$B$10*Inputs!$B$11 -> 0 | C13: =C2*Inputs!$B$9*Inputs!$B$10*Inputs!$B$11 -> 0 | D13: =D2*Inputs!$B$9*Inputs!$B$10*Inputs!$B$11 -> 0 | E13: =E2*Inputs!$B$9*Inputs!$B$10*Inputs!$B$11 -> 53752.8 | F13: =F2*Inputs!$B$9*Inputs!$B$10*Inputs!$B$11 -> 107505.6 | G13: =G2*Inputs!$B$9*Inputs!$B$10*Inputs!$B$11 -> 215011.2 | H13: =H2*Inputs!$B$9*Inputs!$B$10*Inputs!$B$11 -> 322516.8 | I13: =I2*Inputs!$B$9*Inputs!$B$10*Inputs!$B$11 -> 430022.4 | ... M13: =M2*Inputs!$B$9*Inputs!$B$10*Inputs!$B$11 -> 1075056 | N13: =SUM(B13:M13) -> 4300224
A14: Поток до резервов | B14: =B13-B12 -> -2756466 | C14: =C13-C12 -> -2738548.4 | D14: =D13-D12 -> -3768810.4 | E14: =E13-E12 -> -498848.38 | F14: =F13-F12 -> -230084.38 | G14: =G13-G12 -> -140496.38 | H14: =H13-H12 -> -50908.381 | I14: =I13-I12 -> 38679.619 | ... M14: =M13-M12 -> 576207.62 | N14: =SUM(B14:M14) -> -8781326.2
A15: Накопленный поток | B15: =B14 -> -2756466 | C15: =B15+C14 -> -5495014.4 | D15: =C15+D14 -> -9263824.7 | E15: =D15+E14 -> -9762673.1 | F15: =E15+F14 -> -9992757.5 | G15: =F15+G14 -> -10133254 | H15: =G15+H14 -> -10184162 | I15: =H15+I14 -> -10145483 | J15: =I15+J14 -> -10017215 | ... M15: =L15+M14 -> -8781326.2 | N15: =M15 -> -8781326.2
A16: Стоимость на MAU, тг/мес. | B16: =IF(B2=0,"N/A",B12/B2) -> N/A | C16: =IF(C2=0,"N/A",C12/C2) -> N/A | D16: =IF(D2=0,"N/A",D12/D2) -> N/A | E16: =IF(E2=0,"N/A",E12/E2) -> 5526.0118 | F16: =IF(F2=0,"N/A",F12/F2) -> 1687.9499 | G16: =IF(G2=0,"N/A",G12/G2) -> 888.76895 | H16: =IF(H2=0,"N/A",H12/H2) -> 622.3753 | I16: =IF(I2=0,"N/A",I12/I2) -> 489.17848 | ... M16: =IF(M2=0,"N/A",M12/M2) -> 249.42419 | N16: =N12/N2 -> 1635.1938
A17: Риск-резерв, распределение | B17: =ROUND(Inputs!$B$17*Inputs!$B$12/3,2) -> 94366.03 | C17: =ROUND(Inputs!$B$17*Inputs!$B$12/3,2) -> 94366.03 | D17: =Inputs!$B$17*Inputs!$B$12-B17-C17 -> 94366.02 | E17: 0 | F17: 0 | G17: 0 | H17: 0 | I17: 0 | J17: 0 | K17: 0 | L17: 0 | M17: 0 | N17: =SUM(B17:M17) -> 283098.08
A18: Baseline с рисками | B18: =B12+B17 -> 2850832 | C18: =C12+C17 -> 2832914.4 | D18: =D12+D17 -> 3863176.4 | E18: =E12+E17 -> 552601.18 | F18: =F12+F17 -> 337589.98 | G18: =G12+G17 -> 355507.58 | H18: =H12+H17 -> 373425.18 | I18: =I12+I17 -> 391342.78 | ... M18: =M12+M17 -> 498848.38 | N18: =SUM(B18:M18) -> 13364648
A19: Управленческий резерв | B19: 0 | C19: 0 | D19: =Inputs!$B$18*Inputs!$B$12 -> 71670.4 | E19: 0 | F19: 0 | G19: 0 | H19: 0 | I19: 0 | J19: 0 | K19: 0 | L19: 0 | M19: 0 | N19: =SUM(B19:M19) -> 71670.4
A20: Лимит финансирования | B20: =B18+B19 -> 2850832 | C20: =C18+C19 -> 2832914.4 | D20: =D18+D19 -> 3934846.8 | E20: =E18+E19 -> 552601.18 | F20: =F18+F19 -> 337589.98 | G20: =G18+G19 -> 355507.58 | H20: =H18+H19 -> 373425.18 | I20: =I18+I19 -> 391342.78 | ... M20: =M18+M19 -> 498848.38 | N20: =SUM(B20:M20) -> 13436319

Sheet Unit
A1: Показатель | B1: Значение, тг / MAU / доля | C1: Пояснение
A2: Выручка на MAU | B2: =Inputs!$B$9*Inputs!$B$10*Inputs!$B$11 -> 537.528 | C2: Средний чек в тенге × 3% × 8%; после отмен
A3: Переменные расходы на MAU | B3: =Inputs!$B$8 -> 89.588 | C3: Тенге / активный турист / месяц; ставка из Inputs
A4: Вклад MAU | B4: =B2-B3 -> 447.94 | C4: Должен быть >0; иначе конечной точки безубыточности нет
A5: Постоянные затраты/мес. | B5: =Hosting!B12+Inputs!$B$6+Inputs!$B$7 -> 319672.38 | C5: Размещение и его администрирование + поддержка приложения + продвижение, тг/мес.
A6: Разовые затраты | B6: =Inputs!$B$2+Inputs!$B$3+Inputs!$B$4+Inputs!$B$5+Hosting!B14 -> 9335069.6 | C6: Сумма разовых затрат в тенге; в первом году уже включена в Budget12
A7: Разовые / 36 | B7: =B6/Inputs!$B$21 -> 259307.49 | C7: Только для зрелой unit-модели; не добавлять повторно в бюджет
A8: Операционная безубыточность, MAU | B8: =IF(B4<=0,"Нет",ROUNDUP(B5/B4,0)) -> 714 | C8: Рост в пределах подтвержденной мощности
A9: Полная безубыточность, MAU | B9: =IF(B4<=0,"Нет",ROUNDUP((B5+B7)/B4,0)) -> 1293 | C9: С распределением разовых затрат на 36 мес.
A10: Полная с обоими резервами, MAU | B10: =IF(B4<=0,"Нет",ROUNDUP((B5+(B6+Inputs!$B$17*Inputs!$B$12+Inputs!$B$18*Inputs!$B$12)/Inputs!$B$21)/B4,0)) -> 1315 | C10: Резервы — лимит, не расход
A11: MAU для примера | B11: 2000 | C11: Зрелый месяц / M12
A12: Операционный CPU | B12: =B5/B11+B3 -> 249.42419 | C12: (F + vN) / N
A13: Полный CPU | B13: =(B5+B7)/B11+B3 -> 379.07793 | C13: (F + vN + I/36) / N
A14: Операционная прибыль/мес. | B14: =B11*B4-B5 -> 576207.62 | C14: При 2000 MAU
A15: Полный результат/мес. | B15: =B14-B7 -> 316900.13 | C15: Управленческий показатель
A16: Средний CPU первого года | B16: =Budget12!N12/Budget12!N2 -> 1635.1938 | C16: Деление на 8000 пользователь-месяцев, не на 2000 × 12
A17: Средний CPU с рисками | B17: =Budget12!N18/Budget12!N2 -> 1670.581 | C17: Baseline / user-months
A18: Дефицит первого года | B18: =Budget12!N12-Budget12!N13 -> 8781326.2 | C18: Это результат, не максимальная потребность в оборотных средствах
A19: Пиковый кассовый разрыв | B19: =-MIN(Budget12!B15:M15) -> 10184162 | C19: До резервов; при поступлении комиссии в том же месяце
A20: Чистое финансирование с резервами | B20: =B19+Inputs!$B$17*Inputs!$B$12+Inputs!$B$18*Inputs!$B$12 -> 10538931 | C20: Gross лимит сметы Budget12!N20 отдельно, без зачета выручки
A21: Конверсия безубыточности при 2000 MAU | B21: =(B5/B11+B3)/(Inputs!$B$9*Inputs!$B$11) -> 0.013920625 | C21: Операционная, при неизменном среднем чеке и комиссии
A22: Ставка дисконтирования исходного кейса | B22: 0.15 | C22: Только справочно; TCO здесь недисконтированный
A23: MAU каждого из 9 рабочих месяцев для окупаемости за год | B23: =IF(B4<=0,"Нет",ROUNDUP((Budget12!N12-Budget12!N11)/(9*B4),0)) -> 3068 | C23: Без резервов: N1–N3=0, одинаковый MAU M4–M12; выше 2000 — требует новой оценки мощности

Sheet Sensitivity
A1: Сценарий | B1: Конверсия | C1: Комиссия | D1: Расход/MAU, тг | E1: Вклад/MAU, тг | F1: Fixed/мес., тг | G1: MAU операц. | H1: MAU полный
A2: База | B2: =Inputs!$B$10 -> 0.03 | C2: =Inputs!$B$11 -> 0.08 | D2: =Inputs!$B$8 -> 89.588 | E2: =Inputs!$B$9*B2*C2-D2 -> 447.94 | F2: =Unit!B5 -> 319672.38 | G2: =IF(E2<=0,"Нет",ROUNDUP(F2/E2,0)) -> 714 | H2: =IF(E2<=0,"Нет",ROUNDUP((F2+Unit!B7)/E2,0)) -> 1293
A3: Конверсия 2% | B3: 0.02 | C3: =Inputs!$B$11 -> 0.08 | D3: =Inputs!$B$8 -> 89.588 | E3: =Inputs!$B$9*B3*C3-D3 -> 268.764 | F3: =Unit!B5 -> 319672.38 | G3: =IF(E3<=0,"Нет",ROUNDUP(F3/E3,0)) -> 1190 | H3: =IF(E3<=0,"Нет",ROUNDUP((F3+Unit!B7)/E3,0)) -> 2155
A4: Конверсия 1% | B4: 0.01 | C4: =Inputs!$B$11 -> 0.08 | D4: =Inputs!$B$8 -> 89.588 | E4: =Inputs!$B$9*B4*C4-D4 -> 89.588 | F4: =Unit!B5 -> 319672.38 | G4: =IF(E4<=0,"Нет",ROUNDUP(F4/E4,0)) -> 3569 | H4: =IF(E4<=0,"Нет",ROUNDUP((F4+Unit!B7)/E4,0)) -> 6463
A5: Комиссия 5% | B5: =Inputs!$B$10 -> 0.03 | C5: 0.05 | D5: =Inputs!$B$8 -> 89.588 | E5: =Inputs!$B$9*B5*C5-D5 -> 246.367 | F5: =Unit!B5 -> 319672.38 | G5: =IF(E5<=0,"Нет",ROUNDUP(F5/E5,0)) -> 1298 | H5: =IF(E5<=0,"Нет",ROUNDUP((F5+Unit!B7)/E5,0)) -> 2351
A6: Переменные расходы на MAU × 2 | B6: =Inputs!$B$10 -> 0.03 | C6: =Inputs!$B$11 -> 0.08 | D6: =Inputs!$B$8*2 -> 179.176 | E6: =Inputs!$B$9*B6*C6-D6 -> 358.352 | F6: =Unit!B5 -> 319672.38 | G6: =IF(E6<=0,"Нет",ROUNDUP(F6/E6,0)) -> 893 | H6: =IF(E6<=0,"Нет",ROUNDUP((F6+Unit!B7)/E6,0)) -> 1616
A7: Опубликованные cloud-тарифы +30% | B7: =Inputs!$B$10 -> 0.03 | C7: =Inputs!$B$11 -> 0.08 | D7: =Inputs!$B$8 -> 89.588 | E7: =Inputs!$B$9*B7*C7-D7 -> 447.94 | F7: =Unit!B5+(Hosting!B2+Hosting!B3+Hosting!B4+Hosting!B5+Hosting!B6)*0.3 -> 329435.23 | G7: =IF(E7<=0,"Нет",ROUNDUP(F7/E7,0)) -> 736 | H7: =IF(E7<=0,"Нет",ROUNDUP((F7+Unit!B7)/E7,0)) -> 1315
A8: Конверсия 0% / комиссии не согласованы | B8: 0 | C8: =Inputs!$B$11 -> 0.08 | D8: =Inputs!$B$8 -> 89.588 | E8: =Inputs!$B$9*B8*C8-D8 -> -89.588 | F8: =Unit!B5 -> 319672.38 | G8: =IF(E8<=0,"Нет",ROUNDUP(F8/E8,0)) -> Нет | H8: =IF(E8<=0,"Нет",ROUNDUP((F8+Unit!B7)/E8,0)) -> Нет
A10: Курс меняет только валютные тарифы; местные сметные значения в тенге фиксированы
A11: Валютный сценарий | B11: Изменение курса | C11: Курс валюты, тг/ед. | D11: Cloud OPEX, тг/мес. | E11: F, тг/мес. | F11: Cloud TCO 36 мес., тг | G11: MAU операц. | H11: MAU полный
A12: Курс −20% | B12: -0.2 | C12: =FX!$B$4*(1+B12) -> 358.352 | D12: =Hosting!B12+SUM(Hosting!B2:B6)*B12 -> 44399.813 | E12: =Unit!B5+SUM(Hosting!B2:B6)*B12 -> 313163.81 | F12: =D12*36+Hosting!B13+Hosting!B14 -> 1616310.9 | G12: =IF(Unit!B4<=0,"Нет",ROUNDUP(E12/Unit!B4,0)) -> 700 | H12: =IF(Unit!B4<=0,"Нет",ROUNDUP((E12+Unit!B7)/Unit!B4,0)) -> 1279
A13: Курс базовый | B13: 0 | C13: =FX!$B$4*(1+B13) -> 447.94 | D13: =Hosting!B12+SUM(Hosting!B2:B6)*B13 -> 50908.381 | E13: =Unit!B5+SUM(Hosting!B2:B6)*B13 -> 319672.38 | F13: =D13*36+Hosting!B13+Hosting!B14 -> 1850619.3 | G13: =IF(Unit!B4<=0,"Нет",ROUNDUP(E13/Unit!B4,0)) -> 714 | H13: =IF(Unit!B4<=0,"Нет",ROUNDUP((E13+Unit!B7)/Unit!B4,0)) -> 1293
A14: Курс +20% | B14: 0.2 | C14: =FX!$B$4*(1+B14) -> 537.528 | D14: =Hosting!B12+SUM(Hosting!B2:B6)*B14 -> 57416.949 | E14: =Unit!B5+SUM(Hosting!B2:B6)*B14 -> 326180.95 | F14: =D14*36+Hosting!B13+Hosting!B14 -> 2084927.8 | G14: =IF(Unit!B4<=0,"Нет",ROUNDUP(E14/Unit!B4,0)) -> 729 | H14: =IF(Unit!B4<=0,"Нет",ROUNDUP((E14+Unit!B7)/Unit!B4,0)) -> 1308

Sheet SLO
A1: Сценарий | B1: SLO availability/success | C1: SLA availability/success | D1: Минут в месяце | E1: SLO бюджет, мин. | F1: SLA бюджет, мин. | G1: Пример попыток N | H1: SLO ошибок, floor | I1: SLA ошибок, floor | J1: SLO p95 E2E, сек. | K1: SLA p95 E2E, сек. | L1: Бюджет медленных >2 сек.
A2: C1 Каталог/карточка | B2: 0.999 | C2: 0.995 | D2: 43200 | E2: =D2*(1-B2) -> 43.2 | F2: =D2*(1-C2) -> 216 | G2: 200000 | H2: =ROUNDDOWN(ROUND(G2*(1-B2),8),0) -> 200 | I2: =ROUNDDOWN(ROUND(G2*(1-C2),8),0) -> 1000 | J2: 2 | K2: 3 | L2: =ROUNDDOWN(G2*0.05,0) -> 10000
A3: C2 Вход/профиль | B3: 0.998 | C3: 0.995 | D3: 43200 | E3: =D3*(1-B3) -> 86.4 | F3: =D3*(1-C3) -> 216 | G3: 20000 | H3: =ROUNDDOWN(ROUND(G3*(1-B3),8),0) -> 40 | I3: =ROUNDDOWN(ROUND(G3*(1-C3),8),0) -> 100 | J3: 2 | K3: 3 | L3: =ROUNDDOWN(G3*0.05,0) -> 1000
A4: C3 Отправка заявки/результат | B4: 0.997 | C4: 0.995 | D4: 43200 | E4: =D4*(1-B4) -> 129.6 | F4: =D4*(1-C4) -> 216 | G4: 4000 | H4: =ROUNDDOWN(ROUND(G4*(1-B4),8),0) -> 12 | I4: =ROUNDDOWN(ROUND(G4*(1-C4),8),0) -> 20 | J4: 2 | K4: 3 | L4: =ROUNDDOWN(G4*0.05,0) -> 200
A6: Календарных дней | B6: Минут | C6: SLO99.9 budget | D6: SLO99.8 budget | E6: SLO99.7 budget | F6: SLA99.5 budget
A7: 28 | B7: =A7*1440 -> 40320 | C7: =B7*(1-$B$2) -> 40.32 | D7: =B7*(1-$B$3) -> 80.64 | E7: =B7*(1-$B$4) -> 120.96 | F7: =B7*(1-$C$2) -> 201.6
A8: 30 | B8: =A8*1440 -> 43200 | C8: =B8*(1-$B$2) -> 43.2 | D8: =B8*(1-$B$3) -> 86.4 | E8: =B8*(1-$B$4) -> 129.6 | F8: =B8*(1-$C$2) -> 216
A9: 31 | B9: =A9*1440 -> 44640 | C9: =B9*(1-$B$2) -> 44.64 | D9: =B9*(1-$B$3) -> 89.28 | E9: =B9*(1-$B$4) -> 133.92 | F9: =B9*(1-$C$2) -> 223.2

Sheet Checks
A1: Проверка | B1: Результат | C1: Ожидается
A2: Год по статьям минус месяцы | B2: =SUM(Budget12!N3:N11)-Budget12!N12 -> 0 | C2: 0
A3: Baseline минус план/EMV | B3: =Budget12!N18-Budget12!N12-Inputs!$B$17*Inputs!$B$12 -> -1.8044375e-09 | C3: 0
A4: Лимит минус baseline/управление | B4: =Budget12!N20-Budget12!N18-Inputs!$B$18*Inputs!$B$12 -> 3.783498e-10 | C4: 0
A5: Поток = выручка − расходы | B5: =Budget12!N14-Budget12!N13+Budget12!N12 -> 0 | C5: 0
A6: Cloud TCO минус статьи | B6: =Hosting!B15-Hosting!B12*36-Hosting!B13-Hosting!B14 -> 9.4587449e-11 | C6: 0
A7: Own TCO минус статьи | B7: =Hosting!C15-Hosting!C12*36-Hosting!C13-Hosting!C14 -> 0 | C7: 0
A8: Rent TCO минус статьи | B8: =Hosting!D15-Hosting!D12*36-Hosting!D13-Hosting!D14 -> 0 | C8: 0
A9: Разовые затраты не задвоены | B9: =SUM(Budget12!N3:N7)-Unit!B6 -> 0 | C9: 0
A10: Недостающие часы при полном резерве | B10: =MAX(0,Inputs!$B$19+Inputs!$B$17+Inputs!$B$18-Inputs!$B$20) -> 46.2 | C10: 46.2
A11: Порог: N-1 убыточен | B11: =IF((Unit!B8-1)*Unit!B4<Unit!B5,0,1) -> 0 | C11: 0
A12: Порог: N не убыточен | B12: =IF(Unit!B8*Unit!B4>=Unit!B5,0,1) -> 0 | C12: 0
A13: Полный порог: N-1 убыточен | B13: =IF((Unit!B9-1)*Unit!B4<Unit!B5+Unit!B7,0,1) -> 0 | C13: 0
A14: Полный порог: N не убыточен | B14: =IF(Unit!B9*Unit!B4>=Unit!B5+Unit!B7,0,1) -> 0 | C14: 0
A15: Курс положителен | B15: =IF(FX!B4>0,0,1) -> 0 | C15: 0
A16: Тариф VM переведен в тенге | B16: =ROUND(Tariffs!E2-Tariffs!B2*FX!B4,8) -> 0 | C16: 0
A17: Backup fraction без валютной конвертации | B17: =Tariffs!E4-Tariffs!B4 -> 0 | C17: 0
A18: Базовый валютный сценарий: OPEX | B18: =ROUND(Sensitivity!D13-Hosting!B12,8) -> 0 | C18: 0
A19: Базовый валютный сценарий: TCO | B19: =ROUND(Sensitivity!F13-Hosting!B15,8) -> 0 | C19: 0
A20: Распределение риск-резерва в тенге | B20: =ROUND(SUM(Budget12!B17:M17)-Inputs!B17*Inputs!B12,8) -> 0 | C20: 0

Sheet Sources
A1: ID | B1: Источник | C1: URL | D1: Проверено | E1: Использование
A2: S01 | B2: DigitalOcean: официальный калькулятор | C2: https://www.digitalocean.com/pricing/calculator | D2: 23.10.2026 | E2: Расчет без входа и платежей; параметры и снимок — evidence/
A3: S02 | B3: DigitalOcean: Droplets | C3: https://www.digitalocean.com/pricing/droplets | D3: 23.10.2026 | E3: Basic Regular: 2 vCPU / 4 GiB / 80 GiB — $24; мониторинг 1 vCPU / 1 GiB — $6/мес.
A4: S03 | B4: DigitalOcean: Managed Databases | C4: https://www.digitalocean.com/pricing/managed-databases | D4: 23.10.2026 | E4: PostgreSQL Standard Basic Regular, 1 vCPU / 2 GiB, минимум 30 GiB, без standby: $30,45/мес.
A5: S04 | B5: DigitalOcean: Backups Pricing | C5: https://docs.digitalocean.com/products/backups/details/pricing/ | D5: 23.10.2026 | E5: Daily Basic: 30% от стоимости Droplet; $24 × 30% = $7,20/мес.
A6: S05 | B6: DigitalOcean: Spaces | C6: https://www.digitalocean.com/pricing/spaces-object-storage | D6: 23.10.2026 | E6: $5/мес.: 250 GiB, 1 TiB исходящего трафика; сверх лимита $0,02/GiB хранения и $0,01/GiB трафика.
A7: S06 | B7: Hetzner: изменение тарифов с 15.06.2026 | C7: https://docs.hetzner.com/general/infrastructure-and-availability/price-adjustment/ | D7: 23.10.2026 | E7: AX42-1, FSN/HEL: $117,10/мес., setup $59; без IPv4 и налогов. Берется обычный тариф, не limited offering.
A8: S07 | B8: Hetzner: IP pricing | C8: https://docs.hetzner.com/general/infrastructure-and-availability/ipv4-pricing/ | D8: 23.10.2026 | E8: Primary IPv4 dedicated: $1,90/мес., setup $0.
A9: S08 | B9: Hetzner: AX42 | C9: https://www.hetzner.com/dedicated-rootserver/ax42/ | D9: 23.10.2026 | E9: Ryzen 7 PRO 8700GE, 64 GB ECC, 2 × 512 GB NVMe, 1 Gbit/s; конфигурация для открытого стека.
A10: S09 | B10: Google SRE: Implementing SLOs | C10: https://sre.google/workbook/implementing-slos/ | D10: 23.10.2026 | E10: Методическая основа: пользовательский сценарий, SLI, измеримый SLO и пересмотр целей.
A11: S10 | B11: Google SRE: Error Budget Policy | C11: https://sre.google/workbook/error-budget-policy/ | D11: 23.10.2026 | E11: Методическая основа: error budget = 1 − SLO; при исчерпании приоритет получают надежность и безопасность.
A12: S11 | B12: Национальный Банк РК: курс сметы | C12: https://nationalbank.kz/rss/get_rates.cfm?fdate=23.10.2026 | D12: 23.10.2026 | E12: Официальный исторический RSS за 23.10.2026, 447,94 тенге за единицу валюты провайдера; исходный XML сохранен в evidence/nbrk-2026-10-23.xml.
A13: FX01 | B13: Курс перевода в тенге | C13: https://nationalbank.kz/rss/get_rates.cfm?fdate=23.10.2026 | D13: 2026-10-23 | E13: Курс на FX; исходные тарифы сохраняются в валюте публикации, финансовые результаты показаны в тенге
